{"pattern_method": "Adressing", "name_spectro": "OceanInsight", "wl_lim": [350, 800], "spatial_res": [2, 5], "integration_time_ms": 12.0, "height": 600, "width": 800, "mes_ratio": 30, "m": [[1.005059387550367, -0.015462530100575083, -374.1071968852639], [0.01134586321857298, 0.9870909791626794, -102.7917893458918], [1.6382869621633557e-05, -5.198018994794611e-05, 1.0]], "max_height": 335, "max_width": 445, "IP": "ws://192.168.5.60:8000", "port": "8000", "mode_choice": "Simple", "acquisition_method": "Addressed", "Normalisation": false, "data_path": "/media/pi/42E8-01811/ONE-PIX_HUB_test/ONE-PIX_soft/Hypercubes/18_07_2023_14-10-32"}